cls/__init__.py
cls/cls_json.py
cls/debug_util.py
cls/enumeration.py
cls/fcl.py
cls/subtypes.py
cls/types.py
cls_python-0.1.4.dist-info/AUTHORS.rst
cls_python-0.1.4.dist-info/LICENSE
cls_python-0.1.4.dist-info/METADATA
cls_python-0.1.4.dist-info/WHEEL
cls_python-0.1.4.dist-info/top_level.txt
cls_python-0.1.4.dist-info/RECORD
