Metadata-Version: 2.1
Name: cls-python
Version: 0.1.4
Summary: Python implementation of the CLS framework.
Home-page: https://github.com/cls-python/cls-python
Author: Jan Bessai
Author-email: jan.bessai@tu-dortmund.de
License: Apache License (2.0)
Project-URL: Bug Tracker, https://github.com/cls-python/cls-python/issues
Project-URL: Documentation, https://cls-python.github.io/cls-python/readme.html
Project-URL: Source Code, https://github.com/cls-python/cls-python
Keywords: cls-python
Classifier: Development Status :: 3 - Alpha
Classifier: Intended Audience :: Science/Research
Classifier: Intended Audience :: Developers
Classifier: License :: OSI Approved :: Apache Software License
Classifier: Natural Language :: English
Classifier: Programming Language :: Python :: 3.10
Classifier: Programming Language :: Python :: 3.11
Classifier: Operating System :: Microsoft :: Windows
Classifier: Operating System :: Unix
Classifier: Operating System :: MacOS
Requires-Python: >=3.10
License-File: LICENSE
License-File: AUTHORS.rst
